se_agi/__init__.py
se_agi/__version__.py
se_agi/cli.py
se_agi/agents/__init__.py
se_agi/agents/analysis_agent.py
se_agi/agents/base.py
se_agi/agents/creative_agent.py
se_agi/agents/meta_agent.py
se_agi/agents/research_agent.py
se_agi/agents/tool_agent.py
se_agi/core/config.py
se_agi/core/meta_learner.py
se_agi/core/reflection.py
se_agi/core/seagi.py
se_agi/evolution/__init__.py
se_agi/evolution/capability_evolution.py
se_agi/licensing/__init__.py
se_agi/licensing/decorators.py
se_agi/licensing/exceptions.py
se_agi/licensing/license_manager.py
se_agi/licensing/validation.py
se_agi/memory/__init__.py
se_agi/memory/episodic.py
se_agi/memory/semantic.py
se_agi/memory/working.py
se_agi/reasoning/__init__.py
se_agi/reasoning/multimodal.py
se_agi/safety/__init__.py
se_agi/safety/alignment.py
se_agi/safety/monitor.py
se_agi/utils/__init__.py
se_agi/utils/logging.py
se_agi/utils/metrics.py
se_agi-2.1.1.dist-info/licenses/LICENSE
se_agi-2.1.1.dist-info/METADATA
se_agi-2.1.1.dist-info/WHEEL
se_agi-2.1.1.dist-info/entry_points.txt
se_agi-2.1.1.dist-info/top_level.txt
se_agi-2.1.1.dist-info/RECORD
