Metadata-Version: 2.4
Name: se-agi
Version: 2.1.1
Summary: Self-Evolving General AI: The Holy Grail of Autonomous Intelligence
Home-page: https://github.com/krish567366/se-agi
Author: SE-AGI Research Team
Author-email: SE-AGI Research Team <bajpaikrishna715@gmail.com>
Maintainer-email: SE-AGI Research Team <bajpaikrishna715@gmail.com>
License: MIT
Project-URL: Homepage, https://github.com/krish567366/se-agi
Project-URL: Documentation, https://krish567366.github.io/se-agi
Project-URL: Repository, https://github.com/krish567366/se-agi
Project-URL: Issues, https://github.com/krish567366/se-agi/issues
Project-URL: Changelog, https://github.com/krish567366/se-agi/blob/main/CHANGELOG.md
Keywords: artificial-intelligence,machine-learning,agi,autonomous-ai,self-evolving,multi-agent,meta-learning,reasoning,cognitive-architecture
Classifier: Development Status :: 4 - Beta
Classifier: Intended Audience :: Developers
Classifier: Intended Audience :: Science/Research
Classifier: License :: OSI Approved :: MIT License
Classifier: Operating System :: OS Independent
Classifier: Programming Language :: Python :: 3
Classifier: Programming Language :: Python :: 3.9
Classifier: Programming Language :: Python :: 3.10
Classifier: Programming Language :: Python :: 3.11
Classifier: Programming Language :: Python :: 3.12
Classifier: Topic :: Scientific/Engineering :: Artificial Intelligence
Classifier: Topic :: Software Development :: Libraries :: Python Modules
Classifier: Topic :: Software Development :: Libraries :: Application Frameworks
Requires-Python: >=3.9
License-File: LICENSE
Requires-Dist: torch>=2.1.0
Requires-Dist: transformers>=4.30.0
Requires-Dist: accelerate>=0.20.0
Requires-Dist: datasets>=2.14.0
Requires-Dist: numpy>=1.24.0
Requires-Dist: scipy>=1.10.0
Requires-Dist: scikit-learn>=1.3.0
Requires-Dist: networkx>=3.1
Requires-Dist: pydantic>=2.0.1
Requires-Dist: typer>=0.9.0
Requires-Dist: rich>=13.0.0
Requires-Dist: asyncio-mqtt>=0.14.0
Requires-Dist: redis>=4.6.0
Requires-Dist: sqlalchemy>=2.0.1
Requires-Dist: alembic>=1.11.0
Requires-Dist: gymnasium>=0.29.0
Requires-Dist: stable-baselines3>=2.1.0
Requires-Dist: optuna>=3.3.0
Requires-Dist: wandb>=0.15.0
Requires-Dist: tensorboard>=2.13.0
Requires-Dist: huggingface-hub>=0.16.0
Requires-Dist: opencv-python-headless>=4.8.0
Requires-Dist: pillow>=10.0.0
Requires-Dist: librosa>=0.10.0
Requires-Dist: soundfile>=0.12.0
Requires-Dist: httpx>=0.24.0
Requires-Dist: websockets>=11.0.0
Requires-Dist: fastapi>=0.100.0
Requires-Dist: uvicorn>=0.23.0
Requires-Dist: aiofiles>=23.1.0
Requires-Dist: chromadb>=0.4.0
Requires-Dist: faiss-cpu>=1.7.4
Requires-Dist: qdrant-client>=1.4.0
Requires-Dist: python-dotenv>=1.0.0
Requires-Dist: pyyaml>=6.0
Requires-Dist: jsonschema>=4.19.0
Requires-Dist: click>=8.1.0
Requires-Dist: tqdm>=4.65.0
Requires-Dist: psutil>=5.9.0
Requires-Dist: quantummeta-license>=1.0.0
Provides-Extra: dev
Requires-Dist: pytest>=7.4.0; extra == "dev"
Requires-Dist: pytest-asyncio>=0.21.0; extra == "dev"
Requires-Dist: pytest-cov>=4.1.0; extra == "dev"
Requires-Dist: black>=23.7.0; extra == "dev"
Requires-Dist: isort>=5.12.0; extra == "dev"
Requires-Dist: mypy>=1.5.0; extra == "dev"
Requires-Dist: flake8>=6.0.0; extra == "dev"
Provides-Extra: vision
Requires-Dist: opencv-python>=4.8.0; extra == "vision"
Requires-Dist: pillow>=10.0.0; extra == "vision"
Requires-Dist: transformers[vision]>=4.30.0; extra == "vision"
Provides-Extra: audio
Requires-Dist: librosa>=0.10.0; extra == "audio"
Requires-Dist: soundfile>=0.12.0; extra == "audio"
Provides-Extra: simulation
Requires-Dist: gymnasium>=0.29.0; extra == "simulation"
Requires-Dist: pybullet>=3.2.5; extra == "simulation"
Provides-Extra: all
Requires-Dist: se-agi[audio,dev,simulation,vision]; extra == "all"
Dynamic: author
Dynamic: home-page
Dynamic: license-file
Dynamic: requires-python
